histomics_detect/__init__.py
histomics_detect/anchors/__init__.py
histomics_detect/anchors/create.py
histomics_detect/anchors/filter.py
histomics_detect/anchors/sampling.py
histomics_detect/augmentation/__init__.py
histomics_detect/augmentation/augmentation.py
histomics_detect/boxes/__init__.py
histomics_detect/boxes/cross_boxes.py
histomics_detect/boxes/match.py
histomics_detect/boxes/neighborhood.py
histomics_detect/boxes/transforms.py
histomics_detect/io/__init__.py
histomics_detect/io/input.py
histomics_detect/metrics/__init__.py
histomics_detect/metrics/average_precision.py
histomics_detect/metrics/iou.py
histomics_detect/metrics/lnms.py
histomics_detect/metrics/objectness.py
histomics_detect/models/__init__.py
histomics_detect/models/block_model.py
histomics_detect/models/compression_network.py
histomics_detect/models/experiment_utils.py
histomics_detect/models/faster_rcnn.py
histomics_detect/models/lnms_loss.py
histomics_detect/models/lnms_model.py
histomics_detect/models/model_utils.py
histomics_detect/networks/__init__.py
histomics_detect/networks/backbones.py
histomics_detect/networks/fast_rcnn.py
histomics_detect/networks/field_size.py
histomics_detect/networks/rpns.py
histomics_detect/networks/transfer_layers.py
histomics_detect/roialign/__init__.py
histomics_detect/roialign/roialign.py
histomics_detect/visualization/__init__.py
histomics_detect/visualization/lnms_visualization.py
histomics_detect/visualization/visualization.py
histomics_detect-0.0.1.dist-info/entry_points.txt
histomics_detect-0.0.1.dist-info/LICENSE
histomics_detect-0.0.1.dist-info/WHEEL
histomics_detect-0.0.1.dist-info/METADATA
histomics_detect-0.0.1.dist-info/RECORD
