Metadata-Version: 2.1
Name: histomics_detect
Version: 0.0.1
Summary: A TensorFlow 2 package for cell detection
Keywords: histomics_detect,HistomicsDetect
Author-email: "Lee A. D. Cooper" <lee.cooper@northwestern.edu>
Maintainer-email: "Lee A. D. Cooper" <lee.cooper@northwestern.edu>
Requires-Python: >=3.6
Classifier: Programming Language :: Python :: 3
Classifier: License :: OSI Approved :: Apache Software License
Classifier: Topic :: Scientific/Engineering :: Artificial Intelligence
Classifier: Topic :: Scientific/Engineering :: Image Processing
Classifier: Topic :: Scientific/Engineering :: Image Recognition
Requires-Dist: matplotlib
Requires-Dist: numpy
Requires-Dist: pandas
Requires-Dist: Pillow
Requires-Dist: pooch
Requires-Dist: pyyaml
Requires-Dist: scipy
Requires-Dist: tensorflow-gpu>=2.4
Project-URL: Source, https://github.com/DigitalSlideArchive/HistomicsDetect
